Y2F_PACKAGE/Graphical_User_Interface.py
Y2F_PACKAGE/Youtube_Content_Operations.py
Y2F_PACKAGE/__init__.py
Y2F_PACKAGE/main.py
Y2F-1.0.5.dist-info/LICENCE
Y2F-1.0.5.dist-info/METADATA
Y2F-1.0.5.dist-info/WHEEL
Y2F-1.0.5.dist-info/entry_points.txt
Y2F-1.0.5.dist-info/top_level.txt
Y2F-1.0.5.dist-info/RECORD
